csrgraph2/__init__.py
csrgraph2/ggvec.py
csrgraph2/glove.py
csrgraph2/graph.py
csrgraph2/grarep.py
csrgraph2/methods.py
csrgraph2/random_walks.py
csrgraph2/version.py
csrgraph2-0.1.29.dist-info/LICENSE.txt
csrgraph2-0.1.29.dist-info/METADATA
csrgraph2-0.1.29.dist-info/WHEEL
csrgraph2-0.1.29.dist-info/top_level.txt
csrgraph2-0.1.29.dist-info/RECORD
